opv/methods.py
opv/objects.py
opv/runtime.py
opv/storage.py
opv/threads.py
opv/utility.py
opv/modules/__init__.py
opv/modules/cmd.py
opv/modules/fnd.py
opv/modules/irc.py
opv/modules/log.py
opv/modules/mod.py
opv/modules/rss.py
opv/modules/sts.py
opv/modules/tdo.py
opv/modules/thr.py
opv/modules/udp.py
opv-310.data/scripts/opv
opv-310.dist-info/METADATA
opv-310.dist-info/WHEEL
opv-310.dist-info/top_level.txt
opv-310.dist-info/RECORD
