Metadata-Version: 2.1
Name: opv
Version: 310
Summary: Object Programming Version
Author-email: Bart Thate <bthate@dds.nl>
License: Public Domain
Project-URL: home, https://pypi.org/project/opv
Project-URL: bugs, https://github.com/bthate/opv/issues
Project-URL: source, https://github.com/bthate/opv
Classifier: Development Status :: 3 - Alpha
Classifier: License :: Public Domain
Classifier: Operating System :: Unix
Classifier: Programming Language :: Python
Classifier: Topic :: Utilities
